mcp_server_k8s/__init__.py
mcp_server_k8s/__main__.py
mcp_server_k8s/py.typed
mcp_server_k8s/server.py
k8s_mcp_server-0.1.0.dist-info/METADATA
k8s_mcp_server-0.1.0.dist-info/WHEEL
k8s_mcp_server-0.1.0.dist-info/entry_points.txt
k8s_mcp_server-0.1.0.dist-info/top_level.txt
k8s_mcp_server-0.1.0.dist-info/RECORD
