Metadata-Version: 2.4
Name: k8s-mcp-server
Version: 0.1.0
Summary: Add your description here
Author-email: truskovskiyk <truskovskiyk@gmail.com>
Requires-Python: >=3.13
Requires-Dist: asyncio>=3.4.3
Requires-Dist: kubernetes>=32.0.1
Requires-Dist: mcp[cli]>=1.6.0
Requires-Dist: typing>=3.10.0.0
